MANIFEST.in
README.rst
setup.py
collective/.DS_Store
collective/__init__.py
collective/__init__.pyc
collective.ptg.fancybox.egg-info/PKG-INFO
collective.ptg.fancybox.egg-info/SOURCES.txt
collective.ptg.fancybox.egg-info/dependency_links.txt
collective.ptg.fancybox.egg-info/entry_points.txt
collective.ptg.fancybox.egg-info/namespace_packages.txt
collective.ptg.fancybox.egg-info/not-zip-safe
collective.ptg.fancybox.egg-info/requires.txt
collective.ptg.fancybox.egg-info/top_level.txt
collective/ptg/.DS_Store
collective/ptg/__init__.py
collective/ptg/__init__.pyc
collective/ptg/fancybox/.DS_Store
collective/ptg/fancybox/__init__.py
collective/ptg/fancybox/__init__.pyc
collective/ptg/fancybox/configure.zcml
collective/ptg/fancybox/fancybox.pt
collective/ptg/fancybox/i18n.sh
collective/ptg/fancybox/locales/collective.ptg.fancybox.pot
collective/ptg/fancybox/locales/manual.pot
collective/ptg/fancybox/locales/de/LC_MESSAGES/collective.ptg.fancybox.po
collective/ptg/fancybox/locales/es/LC_MESSAGES/collective.ptg.fancybox.po
collective/ptg/fancybox/locales/eu/LC_MESSAGES/collective.ptg.fancybox.po
collective/ptg/fancybox/locales/fi/LC_MESSAGES/collective.ptg.fancybox.po
collective/ptg/fancybox/locales/fr/LC_MESSAGES/collective.ptg.fancybox.po
collective/ptg/fancybox/locales/it/LC_MESSAGES/collective.ptg.fancybox.po
collective/ptg/fancybox/locales/nl/LC_MESSAGES/collective.ptg.fancybox.po
collective/ptg/fancybox/locales/no/LC_MESSAGES/collective.ptg.fancybox.po
collective/ptg/fancybox/locales/pt_BR/LC_MESSAGES/collective.ptg.fancybox.po
collective/ptg/fancybox/resources/.DS_Store
collective/ptg/fancybox/resources/UPDATING.txt
collective/ptg/fancybox/resources/blank.gif
collective/ptg/fancybox/resources/fancy_close.png
collective/ptg/fancybox/resources/fancy_loading.png
collective/ptg/fancybox/resources/fancy_nav_left.png
collective/ptg/fancybox/resources/fancy_nav_right.png
collective/ptg/fancybox/resources/fancy_shadow_e.png
collective/ptg/fancybox/resources/fancy_shadow_n.png
collective/ptg/fancybox/resources/fancy_shadow_ne.png
collective/ptg/fancybox/resources/fancy_shadow_nw.png
collective/ptg/fancybox/resources/fancy_shadow_s.png
collective/ptg/fancybox/resources/fancy_shadow_se.png
collective/ptg/fancybox/resources/fancy_shadow_sw.png
collective/ptg/fancybox/resources/fancy_shadow_w.png
collective/ptg/fancybox/resources/fancy_title_left.png
