Metadata-Version: 1.0
Name: collective.ptg.fancybox
Version: 1.2
Summary: UNKNOWN
Home-page: https://github.com/collective/collective.ptg.fancybox
Author: Nathan Van Gheem
Author-email: vangheem@gmail.com
License: GPL
Keywords: plone plonetruegallery addon fancybox
Platform: UNKNOWN
Classifier: Framework :: Plone
Classifier: Framework :: Plone :: 4.0
Classifier: Framework :: Plone :: 4.3
Classifier: Framework :: Plone :: 5.0
Classifier: Programming Language :: Python
Classifier: Programming Language :: Python
